<?xml version="1.0" encoding="utf-8"?><DEFECTS><DEFECT><SFA><FILEPATH>d:\icho\documents\visual studio 2013\projects\textgameoop\textgameoop\</FILEPATH><FILENAME>message.cpp</FILENAME><LINE>27</LINE><COLUMN>1</COLUMN></SFA><DEFECTCODE>6001</DEFECTCODE><DESCRIPTION>Using uninitialized memory 'bufferWidth'.</DESCRIPTION><FUNCTION>GetBufferWidth</FUNCTION><DECORATED>?GetBufferWidth@@YAHXZ</DECORATED><FUNCLINE>15</FUNCLINE><PROBABILITY>1</PROBABILITY><RANK>3</RANK><CATEGORY><RULECATEGORY>mspft</RULECATEGORY></CATEGORY><PATH><SFA><FILEPATH>d:\icho\documents\visual studio 2013\projects\textgameoop\textgameoop\</FILEPATH><FILENAME>message.cpp</FILENAME><LINE>17</LINE><COLUMN>28</COLUMN></SFA><SFA><FILEPATH>d:\icho\documents\visual studio 2013\projects\textgameoop\textgameoop\</FILEPATH><FILENAME>message.cpp</FILENAME><LINE>18</LINE><COLUMN>5</COLUMN><KEYEVENT><ID>1</ID><KIND>declaration</KIND><IMPORTANCE>Essential</IMPORTANCE><MESSAGE>'bufferWidth' is not initialized</MESSAGE></KEYEVENT></SFA><SFA><FILEPATH>d:\icho\documents\visual studio 2013\projects\textgameoop\textgameoop\</FILEPATH><FILENAME>message.cpp</FILENAME><LINE>18</LINE><COLUMN>18</COLUMN></SFA><SFA><FILEPATH>d:\icho\documents\visual studio 2013\projects\textgameoop\textgameoop\</FILEPATH><FILENAME>message.cpp</FILENAME><LINE>20</LINE><COLUMN>8</COLUMN></SFA><SFA><FILEPATH>d:\icho\documents\visual studio 2013\projects\textgameoop\textgameoop\</FILEPATH><FILENAME>message.cpp</FILENAME><LINE>22</LINE><COLUMN>5</COLUMN><KEYEVENT><ID>2</ID><KIND>branch</KIND><IMPORTANCE>Full</IMPORTANCE><MESSAGE>Skip this branch, (assume 'result' is false)</MESSAGE></KEYEVENT></SFA><SFA><FILEPATH>d:\icho\documents\visual studio 2013\projects\textgameoop\textgameoop\</FILEPATH><FILENAME>message.cpp</FILENAME><LINE>27</LINE><COLUMN>1</COLUMN><KEYEVENT><ID>3</ID><KIND>usage</KIND><IMPORTANCE>Essential</IMPORTANCE><MESSAGE>'bufferWidth' is used, but may not have been initialized</MESSAGE></KEYEVENT></SFA></PATH></DEFECT></DEFECTS>